W3schoolPythonJiaocheng/README.md
W3schoolPythonJiaocheng/__init__.py
W3schoolPythonJiaocheng/__main__.py
W3schoolPythonJiaocheng/file.epub
W3schoolPythonJiaocheng/index.html
W3schoolPythonJiaocheng/css/__init__.py
W3schoolPythonJiaocheng/css/annotations.css
W3schoolPythonJiaocheng/css/main.css
W3schoolPythonJiaocheng/css/normalize.css
W3schoolPythonJiaocheng/css/popup.css
W3schoolPythonJiaocheng/font/__init__.py
W3schoolPythonJiaocheng/font/fontello.eot
W3schoolPythonJiaocheng/font/fontello.svg
W3schoolPythonJiaocheng/font/fontello.ttf
W3schoolPythonJiaocheng/font/fontello.woff
W3schoolPythonJiaocheng/img/__init__.py
W3schoolPythonJiaocheng/img/annotator-glyph-sprite.png
W3schoolPythonJiaocheng/img/annotator-icon-sprite.png
W3schoolPythonJiaocheng/img/apple-touch-icon.png
W3schoolPythonJiaocheng/img/cancelfullscreen.png
W3schoolPythonJiaocheng/img/close.png
W3schoolPythonJiaocheng/img/fullscreen.png
W3schoolPythonJiaocheng/img/loader.gif
W3schoolPythonJiaocheng/img/menu-icon.png
W3schoolPythonJiaocheng/img/save.png
W3schoolPythonJiaocheng/img/saved.png
W3schoolPythonJiaocheng/img/settings-s.png
W3schoolPythonJiaocheng/img/settings.png
W3schoolPythonJiaocheng/img/star.png
W3schoolPythonJiaocheng/js/__init__.py
W3schoolPythonJiaocheng/js/epub.js
W3schoolPythonJiaocheng/js/epub.min.js
W3schoolPythonJiaocheng/js/epub.min.map
W3schoolPythonJiaocheng/js/hooks.min.js
W3schoolPythonJiaocheng/js/hooks.min.map
W3schoolPythonJiaocheng/js/reader.js
W3schoolPythonJiaocheng/js/reader.js.map
W3schoolPythonJiaocheng/js/reader.min.js
W3schoolPythonJiaocheng/js/reader.min.map
W3schoolPythonJiaocheng/js/hooks/__init__.py
W3schoolPythonJiaocheng/js/hooks/extensions/__init__.py
W3schoolPythonJiaocheng/js/hooks/extensions/highlight.js
W3schoolPythonJiaocheng/js/libs/__init__.py
W3schoolPythonJiaocheng/js/libs/jquery.min.js
W3schoolPythonJiaocheng/js/libs/localforage.min.js
W3schoolPythonJiaocheng/js/libs/screenfull.js
W3schoolPythonJiaocheng/js/libs/screenfull.min.js
w3school_python_jiaocheng-2024.3.5.0.dist-info/METADATA
w3school_python_jiaocheng-2024.3.5.0.dist-info/WHEEL
w3school_python_jiaocheng-2024.3.5.0.dist-info/entry_points.txt
w3school_python_jiaocheng-2024.3.5.0.dist-info/top_level.txt
w3school_python_jiaocheng-2024.3.5.0.dist-info/RECORD
